pyDatabases/__init__.py
pyDatabases/auxfuncs.py
pyDatabases/gpyDB/__init__.py
pyDatabases/gpyDB/database.py
pyDatabases/gpyDB/gpyDB.py
pyDatabases/simpleDB/__init__.py
pyDatabases/simpleDB/simpleDB.py
pydatabases-0.2.1.dist-info/licenses/LICENSE
pydatabases-0.2.1.dist-info/METADATA
pydatabases-0.2.1.dist-info/WHEEL
pydatabases-0.2.1.dist-info/top_level.txt
pydatabases-0.2.1.dist-info/RECORD
