Metadata-Version: 2.4
Name: pyDatabases
Version: 0.2.1
Summary: Small collection of database classes based primarily pandas, secondarily scipy and GAMS.
Home-page: https://github.com/ChampionApe/pyDatabases
Author: Rasmus K. Skjødt Berg
Author-email: rasmus.kehlet.berg@econ.ku.dk
Classifier: Programming Language :: Python :: 3
Classifier: License :: OSI Approved :: MIT License
Requires-Python: >=3.10
License-File: LICENSE
Requires-Dist: pandas>=2
Requires-Dist: scipy>=1.1
Requires-Dist: openpyxl
Dynamic: author
Dynamic: author-email
Dynamic: classifier
Dynamic: description
Dynamic: description-content-type
Dynamic: home-page
Dynamic: license-file
Dynamic: requires-dist
Dynamic: requires-python
Dynamic: summary
